gardener.py
symlink_gardener-0.2.4.dist-info/LICENSE
symlink_gardener-0.2.4.dist-info/METADATA
symlink_gardener-0.2.4.dist-info/WHEEL
symlink_gardener-0.2.4.dist-info/entry_points.txt
symlink_gardener-0.2.4.dist-info/top_level.txt
symlink_gardener-0.2.4.dist-info/RECORD
