Metadata-Version: 2.1
Name: symlink-gardener
Version: 0.2.4
Summary: A symlink farm manager akin to GNU Stow
Home-page: https://github.com/benburrill/gardener
Author: Ben Burrill
Author-email: bburrill98+symlink-gardener@gmail.com
License: MIT
Platform: UNKNOWN
Classifier: Programming Language :: Python :: 3
Classifier: Programming Language :: Python :: 3 :: Only
Classifier: License :: OSI Approved :: MIT License
Classifier: Topic :: System :: Archiving :: Packaging
Classifier: Topic :: System :: Filesystems
Classifier: Topic :: Utilities
License-File: LICENSE
Requires-Dist: click (>=8)
